MANIFEST.in
setup.py
cmsplugin_fbalbum/__init__.py
cmsplugin_fbalbum/cms_plugins.py
cmsplugin_fbalbum/models.py
cmsplugin_fbalbum.egg-info/PKG-INFO
cmsplugin_fbalbum.egg-info/SOURCES.txt
cmsplugin_fbalbum.egg-info/dependency_links.txt
cmsplugin_fbalbum.egg-info/not-zip-safe
cmsplugin_fbalbum.egg-info/top_level.txt
cmsplugin_fbalbum/static/cms_plugins/css/colorbox.css
cmsplugin_fbalbum/static/cms_plugins/img/border.png
cmsplugin_fbalbum/static/cms_plugins/img/controls.png
cmsplugin_fbalbum/static/cms_plugins/img/loading.gif
cmsplugin_fbalbum/static/cms_plugins/img/loading_background.png
cmsplugin_fbalbum/static/cms_plugins/img/overlay.png
cmsplugin_fbalbum/static/cms_plugins/js/bootstrap-carousel.js
cmsplugin_fbalbum/static/cms_plugins/js/fbalbum.js
cmsplugin_fbalbum/static/cms_plugins/js/jquery.colorbox-min.js
cmsplugin_fbalbum/static/cms_plugins/js/jquery.min.js
cmsplugin_fbalbum/static/cms_plugins/js/loadAlbum.js
cmsplugin_fbalbum/templates/cms_plugins/fb_album.html
cmsplugin_fbalbum/templates/cms_plugins/fb_album_lightbox.html