Metadata-Version: 1.0
Name: cmsplugin-fbalbum
Version: 0.5.5
Summary: facebook album plugin for django-cms
Home-page: http://github.com/vinitcool76/cmsplugin-fbalbum.git
Author: Vinit Kumar
Author-email: vinit.kumar@changer.nl
License: UNKNOWN
Platform: UNKNOWN
